torch_contour/__init__.py
torch_contour/py.typed
torch_contour/torch_contour.py
torch_contour-1.3.1.dist-info/LICENSE
torch_contour-1.3.1.dist-info/METADATA
torch_contour-1.3.1.dist-info/WHEEL
torch_contour-1.3.1.dist-info/top_level.txt
torch_contour-1.3.1.dist-info/RECORD
