Metadata-Version: 2.1
Name: torch_contour
Version: 1.3.1
Summary: Differentiable contour to image operations with PyTorch
Home-page: https://github.com/antoinehabis/torch_contour
Author: Antoine Habis
Author-email: antoine.habis.tlcm@gmail.com
License: MIT
Keywords: differentiable contour processing,pytorch,machine learning,polygon,shape,mask,distance map,draw contour,hausdorff distance
Classifier: Development Status :: 4 - Beta
Classifier: License :: OSI Approved :: MIT License
Classifier: Natural Language :: English
Classifier: Operating System :: OS Independent
Classifier: Programming Language :: Python :: 3.7
Classifier: Programming Language :: Python :: 3.8
Classifier: Programming Language :: Python :: 3.9
Classifier: Programming Language :: Python :: 3.10
Classifier: Programming Language :: Python :: 3.11
Requires-Python: >=3.7
License-File: LICENSE
Requires-Dist: torch
